passiogo_fix/__init__.py
passiogo_fix/passiogo.py
passiogo_fix-0.0.3.dist-info/licenses/LICENSE
passiogo_fix-0.0.3.dist-info/METADATA
passiogo_fix-0.0.3.dist-info/WHEEL
passiogo_fix-0.0.3.dist-info/top_level.txt
passiogo_fix-0.0.3.dist-info/RECORD
