Metadata-Version: 2.4
Name: passiogo_fix
Version: 0.0.3
Summary: An unofficial Python API for Passio Go allowing anyone to build transit-based applications for hundreds of Universities, Municipalities, Paratransit, and Airports. Based on Andrei Thüler's API, with the vehicle latitude/longitude issue fixed.
Author-email: Antonios Theocharopoulos <antoniostheo06@gmail.com>
License-Expression: MIT
Project-URL: Homepage, https://github.com/AntoniosTheo06/PassioGoVehicleFix
Project-URL: Issues, https://github.com/AntoniosTheo06/PassioGoVehicleFix/issues
Requires-Python: >=3.12
License-File: LICENSE
Dynamic: license-file
